MANIFEST.in
README.rst
setup.py
django_gcm.egg-info/PKG-INFO
django_gcm.egg-info/SOURCES.txt
django_gcm.egg-info/dependency_links.txt
django_gcm.egg-info/not-zip-safe
django_gcm.egg-info/requires.txt
django_gcm.egg-info/top_level.txt
gcm/__init__.py
gcm/admin.py
gcm/api.py
gcm/conf.py
gcm/forms.py
gcm/models.py
gcm/resources.py
gcm/signals.py
gcm/tests.py
gcm/urls.py
gcm/utils.py
gcm/management/__init__.py
gcm/management/commands/__init__.py
gcm/management/commands/gcm_messenger.py
gcm/management/commands/gcm_urls.py
gcm/migrations/0001_initial.py
gcm/migrations/0002_auto__chg_field_device_reg_id__add_unique_device_reg_id.py
gcm/migrations/0003_auto__chg_field_device_reg_id.py
gcm/migrations/__init__.py
gcm/templates/gcm/admin/send_message.html